nafparserpy/__init__.py
nafparserpy/naf_v3.3.1.dtd
nafparserpy/parser.py
nafparserpy/layers/__init__.py
nafparserpy/layers/attribution.py
nafparserpy/layers/causal_relations.py
nafparserpy/layers/chunks.py
nafparserpy/layers/constituency.py
nafparserpy/layers/coreferences.py
nafparserpy/layers/deps.py
nafparserpy/layers/elements.py
nafparserpy/layers/entities.py
nafparserpy/layers/factory.py
nafparserpy/layers/factualities.py
nafparserpy/layers/locations_dates.py
nafparserpy/layers/markables.py
nafparserpy/layers/multiwords.py
nafparserpy/layers/naf_header.py
nafparserpy/layers/opinions.py
nafparserpy/layers/raw.py
nafparserpy/layers/srl.py
nafparserpy/layers/temporal_relations.py
nafparserpy/layers/terms.py
nafparserpy/layers/text.py
nafparserpy/layers/time_expressions.py
nafparserpy/layers/topics.py
nafparserpy/layers/tunits.py
nafparserpy/layers/utils.py
nafparserpy-0.3.1.dist-info/LICENSE
nafparserpy-0.3.1.dist-info/METADATA
nafparserpy-0.3.1.dist-info/WHEEL
nafparserpy-0.3.1.dist-info/top_level.txt
nafparserpy-0.3.1.dist-info/RECORD
