Metadata-Version: 2.1
Name: nafparserpy
Version: 0.3.1
Summary: lxml wrapper for NAF
Author: Sophie Arnoult
Author-email: s.i.arnoult@vu.nl
Maintainer: Sophie Arnoult
Maintainer-email: s.i.arnoult@vu.nl
License: Apache License 2.0
Project-URL: documentation, https://cltl.github.io/nafparserpy/
Project-URL: repository, https://github.com/cltl/nafparserpy
Project-URL: changelog, https://github.com/cltl/nafparserpy/blob/main/Changelog.md
Classifier: Programming Language :: Python :: 3
Classifier: Intended Audience :: Developers
Classifier: License :: OSI Approved :: Apache Software License
Requires-Python: >=3.7
License-File: LICENSE
Requires-Dist: lxml
Provides-Extra: test
Requires-Dist: pytest ; extra == 'test'
